gaitpy/__init__.py
gaitpy/gait.py
gaitpy/signal_features.py
gaitpy/util.py
gaitpy/demo/__init__.py
gaitpy/demo/demo.py
gaitpy/demo/demo_classify_bouts.h5
gaitpy/demo/demo_data.csv
gaitpy/demo/demo_gait_features.csv
gaitpy/demo/demo_plot_contacts.html
gaitpy/model/feature_order.txt
gaitpy/model/model.pkl
gaitpy/tests/__init__.py
gaitpy/tests/test_gait.py
gaitpy/tests/test_signal_features.py
gaitpy/tests/test_util.py
gaitpy-1.6.1.dist-info/LICENSE
gaitpy-1.6.1.dist-info/METADATA
gaitpy-1.6.1.dist-info/WHEEL
gaitpy-1.6.1.dist-info/top_level.txt
gaitpy-1.6.1.dist-info/RECORD
