Metadata-Version: 2.1
Name: gaitpy
Version: 1.6.1
Summary: Read and process raw vertical accelerometry data from a lumbar sensor during gait; calculate clinical gait characteristics.
Home-page: http://github.com/matt002/gaitpy
Author: Matthew Czech
Author-email: czech1117@gmail.com
License: MIT
Keywords: gait,gaitpy,lumbar,waist,sensor,wearable,continuous wavelet,inverted pendulum,czech
Platform: UNKNOWN
Classifier: Programming Language :: Python :: 3.6
Classifier: License :: OSI Approved :: MIT License
Requires-Dist: pandas (==0.20.3)
Requires-Dist: scipy (==1.2.0)
Requires-Dist: numpy (==1.13.3)
Requires-Dist: PyWavelets (==0.5.2)
Requires-Dist: scikit-learn (==0.21.3)
Requires-Dist: statsmodels (==0.8.0)
Requires-Dist: bokeh (==0.12.10)
Requires-Dist: dill (==0.2.7.1)
Requires-Dist: deepdish (==0.3.4)
